{
	"modules":
	{
		"mainboard":
		{
			"overlays":
			{
				"24fj64ga306":
				{
					"linker": "./linker/p24FJ64GA306.gld"
				}
			},

			"libraries": ["pic24"],
			"extra_includes":
			[
				"mainboard/src/core",
				"mainboard/src/mib",
				"mainboard/src/mib/commands",
				"mainboard/src/modules",
				"mainboard/src/momo",
				"mainboard/src/util"
			],

			"hw_compatibility": "con_v3.1",
			"defines":
			{
				"BT_TXRP": "25",
				"BT_RXRP": "20",
				"BT_CTSRP": "12",
				"BT_RTSRP": "4",
				"BT_SOFTWAKEPIN": "D3",
				"BT_HARDWAKEPIN": "D10",
				"BT_CMDPIN": "D2",
				"BT_UART": 1,
				"BT_TIMER": 1
			}
		}
	},

	"module_targets" :
	{
		"mainboard": ["24fj64ga306"]
	}
}